funapi/__init__.py
funbook-0.0.1.dist-info/LICENSE
funbook-0.0.1.dist-info/METADATA
funbook-0.0.1.dist-info/WHEEL
funbook-0.0.1.dist-info/entry_points.txt
funbook-0.0.1.dist-info/top_level.txt
funbook-0.0.1.dist-info/RECORD
